CONTROLLORE_COD.srcs/sources_1/new/controllore_cod.v
`timescale 1ns / 1ps
`define RESET_CONDITION 0
//////////////////////////////////////////////////////////////////////////////////
// Company: 
// Engineer: 
// 
// Create Date: 29.05.2025 14:32:43
// Design Name: 
// Module Name: controllore_cod
// Project Name: 
// Target Devices: 
// Tool Versions: 
// Description: 
// 
// Dependencies: 
// 
// Revision:
// Revision 0.01 - File Created
// Additional Comments:
// 
//////////////////////////////////////////////////////////////////////////////////

//Inizializzo il Modulo
module controllore_cod(
    input CLK,
    input RESETn,
    input [7:0] ing_data,
    output reg [7:0] out_data
    );
    
// Faccio una caratterizzazione degli 8 bit, in base alle richieste effettuate
wire [3:0] instruction = ing_data[7:4];
wire [3:0] data = ing_data[3:0];
reg [3:0] status;
reg [3:0] result;

reg [3:0] PRS;
reg [3:0] NES;

localparam [3:0]
    IDLE=4'd0,
    PASS_THROUGH=4'd1,
    INVERTI_BIT=4'd2,
    SOMMA=4'd3,
    BIT_SHIFT_SX=4'd4,
    BIT_SHIFT_DX=4'd5,
    NAND=4'd6,
    BIT0_INVERTER=4'd7,
    RESET=4'd8,
    IGNORA=4'd15;
always @(posedge CLK) begin
		if(RESETn==`RESET_CONDITION)
			PRS<=RESET;
		else
			PRS<=NES;
end

always @(*) begin
    if (RESETn==`RESET_CONDITION)
       NES<=RESET;
    else 
        begin
              case(PRS)
                    RESET:
                        begin
                           NES=IDLE;
                        end
                    IDLE:
                        begin
                            case(instruction)
                                4'b0000: NES = PASS_THROUGH;
                                4'b0001: NES = INVERTI_BIT;
                                4'b0010: NES = SOMMA;
                                4'b0011: NES = BIT_SHIFT_SX;
                                4'b0100: NES = BIT_SHIFT_DX;
                                4'b0101: NES = NAND;
                                4'b0110: NES = BIT0_INVERTER;
                                4'b0111: NES = RESET;
                                default: NES = IGNORA;
                            endcase
                        end
                    PASS_THROUGH:
                        begin
                            NES=IDLE;
                        end
                    INVERTI_BIT:
                        begin
                            NES=IDLE;
                        end
                    SOMMA:
                        begin
                            NES=IDLE;
                        end
                    BIT_SHIFT_SX:
                        begin
                            NES=IDLE;
                        end
                    BIT_SHIFT_DX:
                        begin
                            NES=IDLE;
                        end
                    NAND:
                        begin
                            NES=IDLE;
                        end
                    BIT0_INVERTER:
                        begin
                            NES=IDLE;
                        end
                    IGNORA:
                        begin
                            NES=IDLE;
                        end
            endcase
      end
end    

always @(posedge CLK) begin
       if (RESETn==`RESET_CONDITION) begin
            status <= 4'b0;
            result <= 4'b0;
            out_data[7:4] <= 4'b0;
            out_data[3:0] <= 4'b0;
       end 
    else 
        begin
              case(PRS)
                    RESET:
                        begin
                           status<=RESET;
                           result<=4'b0;
                        end
                    IDLE: //scelgo di lasciare così il risultato, in una condizione di hold
                        begin
                            status<=IDLE;
                            result<=result;
                        end
                    PASS_THROUGH:
                        begin
                            status<=PASS_THROUGH;
                            result<=data;
                        end
                    INVERTI_BIT:
                        begin
                            status<=INVERTI_BIT;
                            result<=~data;
                        end
                    SOMMA:
                        begin
                            status<=SOMMA;
                            result<=data+1;
                        end
                    BIT_SHIFT_SX:
                        begin
                            status<=BIT_SHIFT_SX;
                            result<=data<<1;
                        end
                    BIT_SHIFT_DX:
                        begin
                            status<=BIT_SHIFT_DX;
                            result<=data>>1;
                        end
                    NAND:
                        begin
                            status<=NAND;
                            result <= {4{~((data[2] & data[0]) & (data[3] & data[1]))}};
                        end
                    BIT0_INVERTER:
                        begin
                            status<=BIT0_INVERTER;
                            result <= (data[0] == 1'b1) ? ~data : data;
                        end
                    IGNORA:
                        begin
                            status<=IGNORA;
                            result<=data;
                        end       
            endcase
            out_data[7:4] <= status;
            out_data[3:0] <= result;
      end
end     
endmodule

CONTROLLORE_COD.srcs/sim_1/new/tb_controllore_cod.v
`timescale 1ns / 1ps
`define RESET_CONDITION 0
//////////////////////////////////////////////////////////////////////////////////
// Company: 
// Engineer: 
// 
// Create Date: 29.05.2025 16:24:51
// Design Name: 
// Module Name: tb_controllore_cod
// Project Name: 
// Target Devices: 
// Tool Versions: 
// Description: 
// 
// Dependencies: 
// 
// Revision:
// Revision 0.01 - File Created
// Additional Comments:
// 
//////////////////////////////////////////////////////////////////////////////////


module tb_controllore_cod();
        reg CLK;
        reg RESETn;
        reg [7:0] ing_data;
        wire [7:0] out_data;
        
controllore_cod uut (
            .CLK(CLK),
            .RESETn(RESETn),
            .ing_data(ing_data),
            .out_data(out_data)
);
localparam period=20;
always #(period/2) CLK<=~CLK;
initial begin
	$dumpfile("waveform.vcd");
	$dumpvars();
	CLK=0;
	RESETn=0; //Reset attivo
    ing_data = 8'b0000_0000;
    // Reset attivo per 40 ns
    #40;
    RESETn = 1;
    // Attesa per uscire da reset
    #20;
    // Pass-through (0000 0001)
    ing_data = 8'b0000_0001; #20;
    // Inverti bit (0001 xxxx)
    ing_data = 8'b0001_1010; #20;
    // Somma +1 (0010 xxxx)
    ing_data = 8'b0010_1111; #20;
    // Shift sinistra (0011 xxxx)
    ing_data = 8'b0011_0101; #20;
    // Shift destra (0100 xxxx)
    ing_data = 8'b0100_1000; #20;
    // NAND (0101 xxxx)
    ing_data = 8'b0101_1101; #20;
    // Bit0 inverter (0110 xxxx), bit0=1
    ing_data = 8'b0110_1111; #20;
    // Bit0 inverter (0110 xxxx), bit0=0
    ing_data = 8'b0110_1010; #20;
    // Reset (0111 xxxx)
    ing_data = 8'b0111_0000; #20;
    // Ignora (1000 xxxx)
    ing_data = 8'b1000_1111; #20;
    // Istruzione non definita (1111 xxxx)
    ing_data = 8'b1111_0000; #20;
	#(period);
	RESETn=0;
	#(2*period);
    $finish;
    end
endmodule

CONTROLLORE_COD.sim/sim_1/behav/xsim/waveform.vcd
$date
   Thu May 29 21:41:51 2025
$end

$version
  2024.2.0
  $dumpfile ("waveform.vcd") 
$end

$timescale
  1ps
$end

$scope module tb_controllore_cod $end
$var reg 1 ! CLK $end
$var reg 1 " RESETn $end
$var reg 8 # ing_data [7:0] $end
$var wire 8 $ out_data [7:0] $end
$scope module uut $end
$var wire 1 % CLK $end
$var wire 1 & RESETn $end
$var wire 8 ' ing_data [7:0] $end
$var reg 8 ( out_data [7:0] $end
$var wire 4 ) instruction [3:0] $end
$var wire 4 * data [3:0] $end
$var reg 4 + status [3:0] $end
$var reg 4 , result [3:0] $end
$var reg 4 - PRS [3:0] $end
$var reg 4 . NES [3:0] $end
$upscope $end
$upscope $end
$enddefinitions $end

#0
$dumpvars
0!
0"
b0 #
bx $
0%
0&
b0 '
bx (
b0 )
b0 *
bx +
bx ,
bx -
b1000 .
$end

#10000
1!
b0 $
1%
b0 (
b0 +
b0 ,
b1000 -

#20000
0!
0%

#30000
1!
1%

#40000
0!
1"
0%
1&
b0 .

#50000
1!
1%
b1000 +
b0 -
b1 .

#60000
0!
b1 #
0%
b1 '
b1 *

#70000
1!
b10000000 $
1%
b10000000 (
b0 +
b1 -
b0 .

#80000
0!
b11010 #
0%
b11010 '
b1 )
b1010 *

#90000
1!
b0 $
1%
b0 (
b1 +
b1010 ,
b0 -
b10 .

#100000
0!
b101111 #
0%
b101111 '
b10 )
b1111 *
b11 .

#110000
1!
b11010 $
1%
b11010 (
b0 +
b11 -
b0 .

#120000
0!
b110101 #
0%
b110101 '
b11 )
b101 *

#130000
1!
b1010 $
1%
b1010 (
b11 +
b110 ,
b0 -
b100 .

#140000
0!
b1001000 #
0%
b1001000 '
b100 )
b1000 *
b101 .

#150000
1!
b110110 $
1%
b110110 (
b0 +
b101 -
b0 .

#160000
0!
b1011101 #
0%
b1011101 '
b101 )
b1101 *

#170000
1!
b110 $
1%
b110 (
b101 +
b0 -
b110 .

#180000
0!
b1101111 #
0%
b1101111 '
b110 )
b1111 *
b111 .

#190000
1!
b1010110 $
1%
b1010110 (
b0 +
b111 -
b0 .

#200000
0!
b1101010 #
0%
b1101010 '
b1010 *

#210000
1!
b110 $
1%
b110 (
b111 +
b1010 ,
b0 -
b111 .

#220000
0!
b1110000 #
0%
b1110000 '
b111 )
b0 *
b1000 .

#230000
1!
b1111010 $
1%
b1111010 (
b0 +
b1000 -
b0 .

#240000
0!
b10001111 #
0%
b10001111 '
b1000 )
b1111 *

#250000
1!
b1010 $
1%
b1010 (
b1000 +
b0 ,
b0 -
b1111 .

#260000
0!
b11110000 #
0%
b11110000 '
b1111 )
b0 *

#270000
1!
b10000000 $
1%
b10000000 (
b0 +
b1111 -
b0 .

#280000
0!
0%

#290000
1!
b0 $
1%
b0 (
b1111 +
b0 -
b1111 .

#300000
0!
0"
0%
0&
b1000 .

#310000
1!
1%
b0 +
b1000 -

